lambda_genai_util/AnthropicBedrockUtil.py
lambda_genai_util/AwsTitanBedrockUtil.py
lambda_genai_util/BedrockUtil.py
lambda_genai_util/CohereBedrockUtil.py
lambda_genai_util/MetaBedrockUtil.py
lambda_genai_util/MistralBedrockUtil.py
lambda_genai_util/TextCompletionUtil.py
lambda_genai_util/__init__.py
lambda_genai_util/model_map.py
lambda_genai_util/prompt_service.py
lambda_genai_util-0.0.6.dist-info/LICENSE.txt
lambda_genai_util-0.0.6.dist-info/METADATA
lambda_genai_util-0.0.6.dist-info/WHEEL
lambda_genai_util-0.0.6.dist-info/top_level.txt
lambda_genai_util-0.0.6.dist-info/RECORD
