Metadata-Version: 2.1
Name: lambda_genai_util
Version: 0.0.6
Summary: Library for GenAI Utility for AWS Based development
Author-email: Biprajeet Kar <biprokvs@gmail.com>
Maintainer-email: Biprajeet Kar <biprokvs@gmail.com>
License: MIT License
Classifier: Programming Language :: Python :: 3
Classifier: License :: OSI Approved :: MIT License
Classifier: Operating System :: OS Independent
Requires-Python: >=3.8
License-File: LICENSE.txt
Requires-Dist: click
